bingoset/__init__.py
bingoset/main.py
bingoset/search_bing_api.py
bingoset/utilities/__init__.py
bingoset/utilities/checks.py
bingoset/utilities/config.py
bingoset-0.1.7.dist-info/entry_points.txt
bingoset-0.1.7.dist-info/LICENSE
bingoset-0.1.7.dist-info/WHEEL
bingoset-0.1.7.dist-info/METADATA
bingoset-0.1.7.dist-info/RECORD
