Metadata-Version: 2.1
Name: bingoset
Version: 0.1.7
Summary: 
Home-page: https://github.com/Akshay090/bingoset
License: MIT
Author: Akshay Ashok
Author-email: aks28id@gmail.com
Requires-Python: >=3.7,<4.0
Classifier: License :: OSI Approved :: MIT License
Classifier: Programming Language :: Python :: 3
Classifier: Programming Language :: Python :: 3.7
Classifier: Programming Language :: Python :: 3.8
Requires-Dist: Pillow (>=7.1.2,<8.0.0)
Requires-Dist: requests (>=2.23.0,<3.0.0)
Requires-Dist: typer[all] (>=0.1.1,<0.2.0)
Project-URL: Repository, https://github.com/Akshay090/bingoset
